tenant_users/__init__.py
tenant_users/constants.py
tenant_users/permissions/__init__.py
tenant_users/permissions/backend.py
tenant_users/permissions/functional.py
tenant_users/permissions/functional.pyi
tenant_users/permissions/migrations/0001_initial.py
tenant_users/permissions/migrations/0002_add_timestamps.py
tenant_users/permissions/migrations/__init__.py
tenant_users/permissions/models.py
tenant_users/permissions/utils.py
tenant_users/py.typed
tenant_users/tenants/__init__.py
tenant_users/tenants/apps.py
tenant_users/tenants/management/__init__.py
tenant_users/tenants/management/commands/__init__.py
tenant_users/tenants/management/commands/create_public_tenant.py
tenant_users/tenants/middleware.py
tenant_users/tenants/migrations/__init__.py
tenant_users/tenants/models.py
tenant_users/tenants/models.pyi
tenant_users/tenants/tasks.py
tenant_users/tenants/utils.py
django_tenant_users-2.2.1.dist-info/LICENSE
django_tenant_users-2.2.1.dist-info/METADATA
django_tenant_users-2.2.1.dist-info/WHEEL
django_tenant_users-2.2.1.dist-info/RECORD
