Metadata-Version: 2.3
Name: django-tenant-users
Version: 2.2.1
Summary: A Django app to extend django-tenants to incorporate global multi-tenant users
License: MIT
Keywords: django,django-tenant-users,multi-tenant,saas,tenant,users
Author: Corvia Technologies, LLC
Author-email: support@corvia.tech
Requires-Python: >=3.9
Classifier: Development Status :: 5 - Production/Stable
Classifier: Environment :: Web Environment
Classifier: Framework :: Django
Classifier: Framework :: Django :: 4.2
Classifier: Framework :: Django :: 5.1
Classifier: Framework :: Django :: 5.2
Classifier: Intended Audience :: Developers
Classifier: License :: OSI Approved :: MIT License
Classifier: Operating System :: OS Independent
Classifier: Programming Language :: Python
Classifier: Programming Language :: Python :: 3
Classifier: Programming Language :: Python :: 3.9
Classifier: Programming Language :: Python :: 3.10
Classifier: Programming Language :: Python :: 3.11
Classifier: Programming Language :: Python :: 3.12
Classifier: Programming Language :: Python :: 3.13
Classifier: Topic :: Internet :: WWW/HTTP
Classifier: Topic :: Internet :: WWW/HTTP :: Dynamic Content
Classifier: Topic :: Software Development :: Libraries :: Python Modules
Classifier: Topic :: Internet :: WWW/HTTP :: Dynamic Content :: Content Management System
Requires-Dist: django (>=4.2)
Requires-Dist: django-tenants (>=3.6,<4.0)
Project-URL: Bug Tracker, https://github.com/Corvia/django-tenant-users/issues
Project-URL: Changelog, https://github.com/Corvia/django-tenant-users/blob/main/CHANGELOG.md
Project-URL: Documentation, https://django-tenant-users.readthedocs.io/
Project-URL: Homepage, https://github.com/Corvia/django-tenant-users
Project-URL: Repository, https://github.com/Corvia/django-tenant-users
